{
  "pools": [
    {
      "rolls": 1,
      "entries": [
        {
          "type": "minecraft:item",
          "name": "minecraft:gold_nugget",
          "functions": [
            {
              "function": "minecraft:set_components",
              "components": {
                "minecraft:custom_name": {
                  "text": "?????",
                  "italic": false
                },
                "minecraft:item_name": "",
                "minecraft:rarity": "common"
              }
            },
            {
              "function": "minecraft:set_custom_data",
              "tag": {
                "looting": {
                  "tier": 2,
                  "name": {
                    "text": "金の欠片",
                    "color": "white"
                  },
                  "lore": [
                    "川でも拾えそう"
                  ]
                },
                "money": {
                  "price": 200
                },
                "loot_table": "dun:gen/items/gold_nugget"
              }
            }
          ]
        }
      ]
    }
  ]
}